oacp/__init__.py
oacp/adaptive_prompting.py
oacp/cli.py
oacp/context.py
oacp/contracts.py
oacp/decorators.py
oacp/errors.py
oacp/events.py
oacp/llm_integration.py
oacp/routing.py
oacp/trace.py
oacp/utils.py
oacp/votes.py
oacp/web.py
oacp/storage/__init__.py
oacp/storage/base.py
oacp/storage/file.py
oacp/storage/postgres.py
oacp/storage/sqlite.py
oacp-0.1.8.dist-info/licenses/LICENSE
oacp-0.1.8.dist-info/METADATA
oacp-0.1.8.dist-info/WHEEL
oacp-0.1.8.dist-info/entry_points.txt
oacp-0.1.8.dist-info/top_level.txt
oacp-0.1.8.dist-info/RECORD
