Metadata-Version: 2.4
Name: OACP
Version: 0.1.8
Summary: Open Agent Compliance Protocol - Governance layer for LangGraph
Author-email: Aditya Jangam <aditya@adityajangam.com>
License-Expression: MIT
Project-URL: Homepage, https://github.com/Aaditya17032002/OACP
Project-URL: Documentation, https://github.com/Aaditya17032002/OACP#readme
Project-URL: Repository, https://github.com/Aaditya17032002/OACP
Project-URL: Issues, https://github.com/Aaditya17032002/OACP/issues
Keywords: langgraph,governance,ai,agents,voting,consensus
Classifier: Development Status :: 4 - Beta
Classifier: Intended Audience :: Developers
Classifier: Programming Language :: Python :: 3
Classifier: Programming Language :: Python :: 3.10
Classifier: Programming Language :: Python :: 3.11
Classifier: Programming Language :: Python :: 3.12
Classifier: Topic :: Software Development :: Libraries :: Python Modules
Classifier: Topic :: Scientific/Engineering :: Artificial Intelligence
Requires-Python: >=3.10
License-File: LICENSE
Requires-Dist: pydantic<3.0.0,>=2.0.0
Requires-Dist: typer<1.0.0,>=0.9.0
Requires-Dist: sqlalchemy<3.0.0,>=2.0.0
Requires-Dist: aiosqlite<1.0.0,>=0.19.0
Requires-Dist: ulid-py<2.0.0,>=1.1.0
Requires-Dist: rich<14.0.0,>=13.0.0
Requires-Dist: langgraph>=0.0.55
Provides-Extra: postgres
Requires-Dist: psycopg[binary]<4.0.0,>=3.1.0; extra == "postgres"
Provides-Extra: web
Requires-Dist: fastapi<1.0.0,>=0.104.0; extra == "web"
Requires-Dist: uvicorn<1.0.0,>=0.24.0; extra == "web"
Provides-Extra: dev
Requires-Dist: pytest<8.0.0,>=7.0.0; extra == "dev"
Requires-Dist: pytest-asyncio<1.0.0,>=0.21.0; extra == "dev"
Requires-Dist: pytest-cov<5.0.0,>=4.0.0; extra == "dev"
Requires-Dist: mypy<2.0.0,>=1.5.0; extra == "dev"
Requires-Dist: ruff<1.0.0,>=0.1.0; extra == "dev"
Requires-Dist: black<24.0.0,>=23.0.0; extra == "dev"
Requires-Dist: pre-commit<4.0.0,>=3.0.0; extra == "dev"
Dynamic: license-file
